openpredict/__init__.py
openpredict/config.py
openpredict/decorators.py
openpredict/loaded_model.py
openpredict/predict_output.py
openpredict/py.typed
openpredict/rdf_utils.py
openpredict/trapi.py
openpredict/trapi_parser.py
openpredict/utils.py
openpredict-0.2.1.dist-info/METADATA
openpredict-0.2.1.dist-info/WHEEL
openpredict-0.2.1.dist-info/licenses/LICENSE.txt
openpredict-0.2.1.dist-info/RECORD
