Metadata-Version: 2.1
Name: openpredict
Version: 0.2.1
Summary: A package to help serve predictions of biomedical concepts associations as Translator Reasoner API.
Project-URL: Homepage, https://github.com/MaastrichtU-IDS/translator-openpredict
Project-URL: Documentation, https://github.com/MaastrichtU-IDS/translator-openpredict
Project-URL: History, https://github.com/MaastrichtU-IDS/translator-openpredict/releases
Project-URL: Tracker, https://github.com/MaastrichtU-IDS/translator-openpredict/issues
Project-URL: Source, https://github.com/MaastrichtU-IDS/translator-openpredict
Author: Arif Yilmaz, Elif
Author-email: Remzi Çelebi <r.celebi@maastrichtuniversity.nl>, Vincent Emonet <vincent.emonet@gmail.com>
License: MIT License
License-File: LICENSE.txt
Keywords: Biomedical Data Translator,Predictions,Python,TRAPI
Classifier: License :: OSI Approved :: MIT License
Classifier: Operating System :: OS Independent
Classifier: Programming Language :: Python :: 3.8
Requires-Python: <3.11,>=3.8
Requires-Dist: fastapi>=0.68.1
Requires-Dist: mlem==0.3.2
Requires-Dist: pydantic>=1.9
Requires-Dist: rdflib>=6.1.1
Requires-Dist: reasoner-pydantic==3.0.1
Requires-Dist: requests>=2.23.0
Requires-Dist: sparqlwrapper<3.0.0,>=2.0.0
Provides-Extra: dev
Requires-Dist: autoflake<2.0.0,>=1.4.0; extra == 'dev'
Requires-Dist: dvc==2.38.1; extra == 'dev'
Requires-Dist: flake8-pyproject>=1.1.0.post0; extra == 'dev'
Requires-Dist: flake8<6.0.0,>=3.8.3; extra == 'dev'
Requires-Dist: flaky; extra == 'dev'
Requires-Dist: isort<6.0.0,>=5.0.6; extra == 'dev'
Requires-Dist: pre-commit<3.0.0,>=2.17.0; extra == 'dev'
Requires-Dist: typer==0.7.0; extra == 'dev'
Requires-Dist: types-requests; extra == 'dev'
Provides-Extra: test
Requires-Dist: httpx; extra == 'test'
Requires-Dist: pytest-cov<4.0.0,>=2.12.0; extra == 'test'
Requires-Dist: pytest<8.0.0,>=7.1.3; extra == 'test'
Requires-Dist: reasoner-validator>=3.1.4; extra == 'test'
Provides-Extra: train
Requires-Dist: cython==0.29.32; extra == 'train'
Requires-Dist: gensim==3.8.3; extra == 'train'
Requires-Dist: matplotlib==3.4.3; extra == 'train'
Requires-Dist: networkx; extra == 'train'
Requires-Dist: numpy==1.16.1; extra == 'train'
Requires-Dist: pandas==1.1.1; extra == 'train'
Requires-Dist: pyrdf2vec==0.0.5; extra == 'train'
Requires-Dist: pyspark==3.1.1; extra == 'train'
Requires-Dist: python-multipart>=0.0.5; extra == 'train'
Requires-Dist: scikit-learn==0.23.1; extra == 'train'
Requires-Dist: scipy==1.5.4; extra == 'train'
Requires-Dist: shap==0.41.0; extra == 'train'
Requires-Dist: torch==1.13.1; extra == 'train'
